{
  "WorkItem": {
    "AffectedComponent": {
      "Name": "TreeViewEx",
      "DisplayName": "TreeViewEx"
    },
    "ClosedComment": "",
    "ClosedDate": "2012-11-07T12:02:17.06-08:00",
    "CommentCount": 0,
    "Custom": null,
    "Description": "I tried extracting the zip file but windows states it is not valid.  If I open it up it is blank.",
    "LastUpdatedDate": "2013-05-16T01:29:10.517-07:00",
    "PlannedForRelease": "TreeViewEx 0.9",
    "ReleaseVisibleToPublic": true,
    "Priority": {
      "Name": "Low",
      "Severity": 50,
      "Id": 1
    },
    "ProjectName": "treeviewex",
    "ReportedDate": "2012-10-31T13:51:12.963-07:00",
    "Status": {
      "Name": "Closed",
      "Id": 4
    },
    "ReasonClosed": {
      "Name": "Unassigned"
    },
    "Summary": "Invalid Zip File",
    "Type": {
      "Name": "Issue",
      "Id": 3
    },
    "VoteCount": 1,
    "Id": 23572
  },
  "FileAttachments": [],
  "Comments": [
    {
      "Message": "It did work with winrar but not with windows default extraction. Ive repacked it with windows tools, so it should work now.",
      "PostedDate": "2012-11-01T06:35:49.373-07:00",
      "Id": -2147483648
    },
    {
      "Message": "",
      "PostedDate": "2012-11-07T12:02:17.06-08:00",
      "Id": -2147483648
    },
    {
      "Message": "",
      "PostedDate": "2013-02-14T12:22:33.41-08:00",
      "Id": -2147483648
    },
    {
      "Message": "",
      "PostedDate": "2013-05-16T01:29:10.517-07:00",
      "Id": -2147483648
    }
  ]
}